{
  "customComponentSupportVersion": "2",
  "components": {
    "HtmlEditor": {
      "name": "Html Editor",
      "model": [
        {
          "name": "value",
          "type": "string"
        }
      ],
      "events": [],
      "defaultHeight": 5,
      "defaultWidth": 2
    },
    "MarkdownEditor": {
      "name": "Markdown Editor",
      "model": [
        {
          "name": "value",
          "type": "string"
        }
      ],
      "events": [],
      "defaultHeight": 5,
      "defaultWidth": 2
    }
  }
}